or2ywtool/OR2YWCore.py
or2ywtool/__main__.py
or2ywtool/yesworkflow-0.2.2.0-SNAPSHOT-jar-with-dependencies.jar
or2ywtool/yw.properties
or2ywtool-0.0.18.dist-info/METADATA
or2ywtool-0.0.18.dist-info/WHEEL
or2ywtool-0.0.18.dist-info/entry_points.txt
or2ywtool-0.0.18.dist-info/top_level.txt
or2ywtool-0.0.18.dist-info/RECORD
