Metadata-Version: 2.1
Name: or2ywtool
Version: 0.0.18
Summary: OR2YW Tool
Home-page: https://github.com/LanLi2017/OR2YWTool
Author: Lan,Li; Parulian, Nikolaus; Ludaescher Bertram
Classifier: Development Status :: 3 - Alpha
Classifier: Intended Audience :: Developers
Classifier: Topic :: Software Development :: Build Tools
Classifier: License :: OSI Approved :: MIT License
Classifier: Programming Language :: Python :: 3
Classifier: Programming Language :: Python :: 3.4
Classifier: Programming Language :: Python :: 3.5
Classifier: Programming Language :: Python :: 3.6
Requires-Dist: networkx
